ProjectRoot/ProjectRoot.py
ProjectRoot/__init__.py
ProjectRoot-0.0.6.dist-info/METADATA
ProjectRoot-0.0.6.dist-info/WHEEL
ProjectRoot-0.0.6.dist-info/top_level.txt
ProjectRoot-0.0.6.dist-info/RECORD
